{
	"configurations" : 
	[
		{
			"directories" : 
			[
				{
					"build" : ".",
					"jsonFile" : "directory-.-Debug-d0094a50bb2071803777.json",
					"minimumCMakeVersion" : 
					{
						"string" : "3.28"
					},
					"projectIndex" : 0,
					"source" : ".",
					"targetIndexes" : 
					[
						0
					]
				}
			],
			"name" : "Debug",
			"projects" : 
			[
				{
					"directoryIndexes" : 
					[
						0
					],
					"name" : "poker_bots",
					"targetIndexes" : 
					[
						0
					]
				}
			],
			"targets" : 
			[
				{
					"directoryIndex" : 0,
					"id" : "poker_bots::@6890427a1f51a3e7e1df",
					"jsonFile" : "target-poker_bots-Debug-6f07e651898ec2efb2c0.json",
					"name" : "poker_bots",
					"projectIndex" : 0
				}
			]
		}
	],
	"kind" : "codemodel",
	"paths" : 
	{
		"build" : "C:/CS Projects/poker-bots/misc/cmake-build-debug",
		"source" : "C:/CS Projects/poker-bots/misc"
	},
	"version" : 
	{
		"major" : 2,
		"minor" : 6
	}
}
